devnotify/__init__.py
devnotify/client.py
devnotify/config.py
devnotify/exceptions.py
devnotify-0.1.0.dist-info/METADATA
devnotify-0.1.0.dist-info/WHEEL
devnotify-0.1.0.dist-info/licenses/LICENSE
devnotify-0.1.0.dist-info/RECORD
