Metadata-Version: 2.4
Name: devnotify
Version: 0.1.0
Summary: Send phone notifications from your code via DevNotify
Project-URL: Homepage, https://devnotify.dev
Author: Your Name
License: ---
License-File: LICENSE
Requires-Python: >=3.8
Requires-Dist: requests>=2.31
Provides-Extra: dev
Requires-Dist: black; extra == 'dev'
Requires-Dist: coverage; extra == 'dev'
Requires-Dist: mypy; extra == 'dev'
Requires-Dist: pytest; extra == 'dev'
Requires-Dist: pytest-cov; extra == 'dev'
Requires-Dist: ruff; extra == 'dev'
Requires-Dist: types-requests; extra == 'dev'
